Metadata-Version: 2.1
Name: django-healthz
Version: 0.0.5
Summary: Simple middleware for healthchecks
Home-page: https://github.com/rehive/django-healthz
Author: Rehive
Author-email: info@rehive.com
License: MIT
Download-URL: https://github.com/rehive/django-healthz/archive/0.0.5.zip
Platform: UNKNOWN
Classifier: Framework :: Django
Classifier: Framework :: Django :: 2.2
Classifier: Intended Audience :: Developers
Classifier: Operating System :: OS Independent
Classifier: License :: OSI Approved :: MIT License
Classifier: Programming Language :: Python
Classifier: Programming Language :: Python :: 3.5
Classifier: Programming Language :: Python :: 3.6
Classifier: Topic :: Internet :: WWW/HTTP
Classifier: Topic :: Internet :: WWW/HTTP :: Dynamic Content
Requires-Python: >=3.4
